livysubmit/__init__.py
livysubmit/__main__.py
livysubmit/livysubmit.py
Livy_Submit-1.1.0.dist-info/LICENSE
Livy_Submit-1.1.0.dist-info/METADATA
Livy_Submit-1.1.0.dist-info/WHEEL
Livy_Submit-1.1.0.dist-info/entry_points.txt
Livy_Submit-1.1.0.dist-info/top_level.txt
Livy_Submit-1.1.0.dist-info/RECORD
