Metadata-Version: 2.1
Name: Livy-Submit
Version: 1.1.0
Summary: Livy-Submit enables you to send your python files to a spark cluster using Livy running on edge node
Home-page: https://github.com/gdiepen/livy-submit
Author: Guido Diepen
Author-email: site-github@guidodiepen.nl
License: MIT
Platform: UNKNOWN
Classifier: Development Status :: 4 - Beta
Classifier: Environment :: Console
Classifier: Intended Audience :: Developers
Classifier: Natural Language :: English
Classifier: Topic :: Software Development :: Build Tools
Classifier: License :: OSI Approved :: MIT License
Classifier: Programming Language :: Python :: 3
Classifier: Programming Language :: Python :: 3.6
Classifier: Programming Language :: Python :: 3.7
